afpapi
